data/questions.json
search_algorithms/__init__.py
search_algorithms/__main__.py
search_algorithms/config.py
search_algorithms/cli/__init__.py
search_algorithms/cli/commands.py
search_algorithms/cli/menu.py
search_algorithms/core/__init__.py
search_algorithms/core/search_algorithms.py
search_algorithms/utils/__init__.py
search_algorithms/utils/data_handler.py
search_algorithms/utils/input_handler.py
search_algorithms_explainer-1.0.1.dist-info/licenses/LICENSE
search_algorithms_explainer-1.0.1.dist-info/METADATA
search_algorithms_explainer-1.0.1.dist-info/WHEEL
search_algorithms_explainer-1.0.1.dist-info/entry_points.txt
search_algorithms_explainer-1.0.1.dist-info/top_level.txt
search_algorithms_explainer-1.0.1.dist-info/RECORD
