Metadata-Version: 2.4
Name: search-algorithms-explainer
Version: 1.0.1
Summary: Interactive CLI tool for exploring search algorithms
Home-page: https://github.com/yourusername/search-algorithms-explainer
Author: Your Name
Author-email: Your Name <your.email@example.com>
License: MIT
Project-URL: Homepage, https://github.com/yourusername/search-algorithms-explainer
Classifier: Development Status :: 4 - Beta
Classifier: Intended Audience :: Education
Classifier: Topic :: Education
Classifier: License :: OSI Approved :: MIT License
Classifier: Programming Language :: Python :: 3
Classifier: Operating System :: OS Independent
Requires-Python: >=3.7
License-File: LICENSE
Dynamic: author
Dynamic: home-page
Dynamic: license-file
Dynamic: requires-python
